blackline/adapters/mysql/__init__.py
blackline/adapters/mysql/mysql.py
blackline/models/mysql/__init__.py
blackline/models/mysql/mysql.py
tests/conftest.py
tests/test_mysql_integration.py
tests/adapters/mysql/test_mysql_adapter.py
tests/models/mysql/test_mysql.py
blackline_mysql-0.1.2.dist-info/METADATA
blackline_mysql-0.1.2.dist-info/WHEEL
blackline_mysql-0.1.2.dist-info/top_level.txt
blackline_mysql-0.1.2.dist-info/RECORD
