Metadata-Version: 2.1
Name: blackline-mysql
Version: 0.1.2
Summary: Manage personal data in your data stores.
Home-page: https://github.com/blacklinedata/blackline-core/tree/main/blackline/mysql
Classifier: Development Status :: 3 - Alpha
Classifier: Intended Audience :: Developers
Classifier: License :: OSI Approved :: Apache Software License
Classifier: Operating System :: MacOS :: MacOS X
Classifier: Operating System :: POSIX :: Linux
Classifier: Programming Language :: Python :: 3.9
Classifier: Programming Language :: Python :: 3.10
Classifier: Programming Language :: Python :: 3.11
Classifier: Topic :: Software Development :: Libraries :: Python Modules
Classifier: Topic :: Utilities
Requires-Python: <3.12,>=3.9
Requires-Dist: blackline-core (==0.1.2)
Requires-Dist: mysql-connector-python (==8.0.32)
Provides-Extra: dev
Requires-Dist: pre-commit (==2.20.0) ; extra == 'dev'
Requires-Dist: pytest (==7.2.0) ; extra == 'dev'
Requires-Dist: bumpver (==2022.1120) ; extra == 'dev'
Requires-Dist: black (==22.12.0) ; extra == 'dev'
Requires-Dist: isort (==5.11.4) ; extra == 'dev'
Requires-Dist: types-PyYAML (==6.0.12.2) ; extra == 'dev'
Requires-Dist: tox (==4.3.1) ; extra == 'dev'
Requires-Dist: prettytable (==3.6.0) ; extra == 'dev'
Requires-Dist: pdbpp ; extra == 'dev'
